example_package_oren/__init__.py
example_package_oren/example.py
datagen_example_pypi-0.0.4.dist-info/LICENSE
datagen_example_pypi-0.0.4.dist-info/METADATA
datagen_example_pypi-0.0.4.dist-info/WHEEL
datagen_example_pypi-0.0.4.dist-info/top_level.txt
datagen_example_pypi-0.0.4.dist-info/RECORD
